odoo/addons/l10n_es_irnr/README.rst
odoo/addons/l10n_es_irnr/__init__.py
odoo/addons/l10n_es_irnr/__manifest__.py
odoo/addons/l10n_es_irnr/data/account_data.xml
odoo/addons/l10n_es_irnr/data/fiscal_position_taxes_irnr.xml
odoo/addons/l10n_es_irnr/data/fiscal_positions_irnr.xml
odoo/addons/l10n_es_irnr/data/taxes_irnr.xml
odoo/addons/l10n_es_irnr/i18n/l10n_es_irnr.pot
odoo/addons/l10n_es_irnr/migrations/13.0.1.0.1/pre-migration.py
odoo/addons/l10n_es_irnr/readme/CONFIGURE.rst
odoo/addons/l10n_es_irnr/readme/CONTRIBUTORS.rst
odoo/addons/l10n_es_irnr/readme/DESCRIPTION.rst
odoo/addons/l10n_es_irnr/readme/ROADMAP.rst
odoo/addons/l10n_es_irnr/readme/USAGE.rst
odoo/addons/l10n_es_irnr/static/description/icon.png
odoo/addons/l10n_es_irnr/static/description/index.html
odoo13_addon_l10n_es_irnr-13.0.1.0.2.dist-info/METADATA
odoo13_addon_l10n_es_irnr-13.0.1.0.2.dist-info/WHEEL
odoo13_addon_l10n_es_irnr-13.0.1.0.2.dist-info/top_level.txt
odoo13_addon_l10n_es_irnr-13.0.1.0.2.dist-info/RECORD
